ezorm/__init__.py
ezorm/config.py
ezorm/configuration.py
ezorm/core.py
ezorm/crud.py
ezorm/db_management.py
ezorm/engine.py
ezorm/utils.py
ezorm/validation.py
ezorm/variables.py
ezorm-0.1.3.dist-info/LICENSE
ezorm-0.1.3.dist-info/METADATA
ezorm-0.1.3.dist-info/WHEEL
ezorm-0.1.3.dist-info/top_level.txt
ezorm-0.1.3.dist-info/RECORD
