Metadata-Version: 2.1
Name: ezorm
Version: 0.1.3
Summary: This library is for people who wanna try interactive with database in an easy way.
Requires-Python: >=3.10
License-File: LICENSE
Requires-Dist: duckdb>=1.1.3
Requires-Dist: pandas>=2.2.3
Requires-Dist: pydantic>=2.10.2
